pyscade/__init__.py
pyscade-0.1.0.dist-info/METADATA
pyscade-0.1.0.dist-info/WHEEL
pyscade-0.1.0.dist-info/RECORD
