Metadata-Version: 2.1
Name: pyscade
Version: 0.1.0
Summary: CSS-like cascading selectors for Python
License: MIT
Author: Ygor Mutti
Author-email: ygormutti@gmail.com
Requires-Python: >=3.8,<4.0
Classifier: License :: OSI Approved :: MIT License
Classifier: Programming Language :: Python :: 3
Classifier: Programming Language :: Python :: 3.8
Classifier: Programming Language :: Python :: 3.9
Classifier: Programming Language :: Python :: 3.10
Classifier: Programming Language :: Python :: 3.11
